{
  "boType": "COMMUNICATION_DATA",
  "structureVersion": "1",
  "validity": "1941-05-05T11:34:31.0Z",
  "communicationDataSheetInactive": false,
  "marketParticipant": {
    "boType": "MARKET_PARTICIPANT",
    "structureVersion": "1",
    "businessPartnerRole": "SUPPLIER",
    "salutation": "Frau",
    "name1": "Cronjäger",
    "name2": "Korbinian",
    "name3": "officia commodo Excepteur",
    "name4": "nulla Ut",
    "partnerAddress": {
      "postalCode": "64802",
      "city": "West Emelieburg",
      "street": "Auf dem Lehn",
      "houseNumber": "33",
      "poBox": "officia",
      "addressSupplement": "irure cupidatat aliquip magna proident",
      "coSupplement": "ipsum sed nisi pariatur quis",
      "countryCode": "CI",
      "district": "Emirdorf",
      "additionalInformation": {
        "supplement1": "Excepteur",
        "supplement2": "eu ut consectetur Duis",
        "supplement3": "est elit in irure",
        "supplement4": "non laborum aliquip dolor",
        "supplement5": "dolor exercitation Duis"
      }
    },
    "commercialClassification": true,
    "externalCustomerNumberSupplier": "dolor Excepteur incididunt",
    "marketRole": "UENB",
    "roleCodeNumber": "342654552",
    "roleCodeType": "BDEW",
    "vatId": "DE011001010",
    "taxNumber": "270419426",
    "contactPerson": {
      "boType": "CONTACT_PERSON",
      "structureVersion": "1",
      "lastName": "Dingelstedt",
      "eMailAddress": "Theodor.Rose@gmail.com",
      "phoneNumbers": [
        {
          "numberType": "DEPARTMENT_FAX",
          "phoneNumber": "+49-5528-89096402"
        }
      ]
    },
    "makoAddress": "anim est",
    "certificateDownloadLink": "https://bahnbrechend-tor.info",
    "courtOfRegistration": "Velbert",
    "commercialRegisterNumber": "828536",
    "website": "https://umwerfend-alphabet.org/",
    "faxNumber": "(07398) 0471614",
    "communicationRole": "CHANGE_PROCESSES",
    "subContracted": false,
    "communicationParameters": {
      "targetAddress": {
        "targetAddress1": "non Ut quis laboris",
        "targetAddress2": "velit sunt commodo aute sed",
        "targetAddress3": "aute",
        "targetAddress4": "sint laboris",
        "targetAddress5": "amet"
      },
      "certificateIssuer": {
        "certificateIssuer1": "Duis laboris ea ad",
        "certificateIssuer2": "amet in",
        "certificateIssuer3": "proident",
        "certificateIssuer4": "nostrud esse enim",
        "certificateIssuer5": "anim ipsum in"
      },
      "certificateUser": {
        "certificateUser1": "ut culpa",
        "certificateUser2": "consequat laborum",
        "certificateUser3": "adipisicing irure mollit quis",
        "certificateUser4": "tempor laborum Excepteur",
        "certificateUser5": "esse cillum Lorem"
      }
    },
    "meteringPointOperatorAttribute": "DEFAULT_METERING_POINT_OPERATOR",
    "bankAccount": [
      {
        "purposeOfUse": "BV_PAYMENT_UNLOCK_BILLING",
        "iban": "FR510034058682A1ZJ7Y6B8G687",
        "accountHolder": "Frau Veronika Gebhardt",
        "bic": "GQHBAXNJ",
        "creditInstitution": "Hamann KG"
      }
    ],
    "reachability": [
      {
        "availability": "THURSDAY",
        "time": "do"
      }
    ],
    "ipAddress": "72.115.67.84",
    "ipRange": {
      "lowerLimit": "c8ba:bef5:b5d4:ece5:dbcc:62bd:f3c7:f0b0",
      "upperLimit": "33.226.182.130"
    },
    "assignmentFrom": "1909-04-19T01:05:32.0Z",
    "assignmentTo": "1892-09-27T21:01:31.0Z",
    "balancingGroup": "irure reprehenderit nulla veniam adipisicing",
    "balancingGroupPurpose": "OTHER_GENERATING_MARKET_LOCATION"
  },
  "communicationDetails": [
    {
      "boType": "MARKET_PARTICIPANT",
      "structureVersion": "1",
      "businessPartnerRole": "CUSTOMER",
      "salutation": "Frau",
      "name1": "Klaus",
      "name2": "Ariane",
      "name3": "reprehenderit Duis culpa",
      "name4": "nulla fugiat",
      "partnerAddress": {
        "postalCode": "78349",
        "city": "Ost Stinaburg",
        "street": "Lötzener Str.",
        "houseNumber": "1",
        "poBox": "consectetur",
        "addressSupplement": "consectetur laborum aliqua mollit consequat",
        "coSupplement": "dolor tempor cillum",
        "countryCode": "GI",
        "district": "Marekstadt",
        "additionalInformation": {
          "supplement1": "do pariatur in commodo",
          "supplement2": "ullamco est",
          "supplement3": "dolore ad",
          "supplement4": "pariatur ut ullamco",
          "supplement5": "aute"
        }
      },
      "commercialClassification": false,
      "externalCustomerNumberSupplier": "est nisi culpa",
      "marketRole": "MSBA",
      "roleCodeNumber": "263117115",
      "roleCodeType": "GLN",
      "vatId": "DE000001110",
      "taxNumber": "500759685",
      "contactPerson": {
        "boType": "CONTACT_PERSON",
        "structureVersion": "1",
        "lastName": "Manns",
        "eMailAddress": "Sanja.Hiebl@yahoo.com",
        "phoneNumbers": [
          {
            "numberType": "DEPARTMENT_PHONE",
            "phoneNumber": "(0893) 902521065"
          }
        ]
      },
      "makoAddress": "laboris amet",
      "certificateDownloadLink": "https://arbeitswutig-comic.net",
      "courtOfRegistration": "Alt Loreen",
      "commercialRegisterNumber": "502268",
      "website": "https://heiblutig-proton.de/",
      "faxNumber": "+49-3101-60822448",
      "communicationRole": "DATA_EXCHANGE",
      "subContracted": true,
      "communicationParameters": {
        "targetAddress": {
          "targetAddress1": "nisi Duis quis consequat et",
          "targetAddress2": "labore ad Excepteur",
          "targetAddress3": "deserunt Duis",
          "targetAddress4": "esse nulla laborum sint dolore",
          "targetAddress5": "id sit"
        },
        "certificateIssuer": {
          "certificateIssuer1": "et ullamco esse eiusmod",
          "certificateIssuer2": "nostrud et nulla dolore eu",
          "certificateIssuer3": "proident incididunt",
          "certificateIssuer4": "ad deserunt",
          "certificateIssuer5": "nostrud Excepteur"
        },
        "certificateUser": {
          "certificateUser1": "veniam eu Duis",
          "certificateUser2": "ullamco enim do",
          "certificateUser3": "minim ut",
          "certificateUser4": "sit dolor",
          "certificateUser5": "aliqua ullamco consequat ex Excepteur"
        }
      },
      "meteringPointOperatorAttribute": "DEFAULT_METERING_POINT_OPERATOR",
      "bankAccount": [
        {
          "purposeOfUse": "BV_PAYMENT_UNLOCK_BILLING",
          "iban": "CR15300987061470800753",
          "accountHolder": "Dr. Colin Schieskow",
          "bic": "IPTKYTIIXXX",
          "creditInstitution": "Camara, Mikitenko und Christ"
        }
      ],
      "reachability": [
        {
          "availability": "TUESDAY",
          "time": "incididunt et"
        }
      ],
      "ipAddress": "dbaf:247d:72a2:8acc:dde7:af13:87ed:c666",
      "ipRange": {
        "lowerLimit": "38.202.184.116",
        "upperLimit": "479d:9d7d:a568:abde:21ac:cabb:bb2d:940c"
      },
      "assignmentFrom": "1929-09-30T23:08:13.0Z",
      "assignmentTo": "1907-01-07T01:28:50.0Z",
      "balancingGroup": "sit",
      "balancingGroupPurpose": "CONSUMING_MARKET_LOCATION"
    }
  ]
}