{
  "$schema": "https://json-schema.org/draft/2020-12/schema",
  "$id": "https://raw.githubusercontent.com/conuti-gmbh/bo4e-schema-en/main/schemas/v1/com/ProductPackage.schema.json",
  "title": "ProductPackage",
  "type": "object",
  "properties": {
    "productPackageId": {
      "type": "integer"
    },
    "product": {
      "type": [
        "array",
        "null"
      ],
      "items": {
        "$ref": "../com/Product.schema.json"
      }
    },
    "implementationLevelRequirement": {
      "$ref": "../enum/ImplementationLevelRequirement.schema.json"
    },
    "prioritization": {
      "$ref": "../enum/Prioritization.schema.json"
    }
  }
}